Metadata-Version: 2.1
Name: dictionary-search
Version: 1.1.0
Summary: Small dictionary search utils
Home-page: https://github.com/cr0hn/python-dictionary-search
Author: Daniel Garcia / Cesar Gallego
Maintainer: Daniel Garcia (cr0hn)
Maintainer-email: cr0hn@cr0hn.com
License: License :: OSI Approved :: MIT License
Platform: UNKNOWN
Classifier: License :: OSI Approved :: MIT License
Classifier: Programming Language :: Python :: 3.7
Classifier: Programming Language :: Python :: 3.8
Classifier: Programming Language :: Python :: 3.9
Classifier: Programming Language :: Python :: 3.10
Classifier: Programming Language :: Python :: 3.11
Classifier: Environment :: Console
Classifier: Operating System :: POSIX
Classifier: Operating System :: MacOS
Classifier: Operating System :: OS Independent
Classifier: Operating System :: Microsoft :: Windows
Classifier: Intended Audience :: Other Audience
Classifier: Intended Audience :: System Administrators
